Workbook

Sheet Presupuesto
A1: Presupuesto
A3: Presupuesto | B3: 1101030 | C3: PLAN DE MANTENIMIENTO-PANAILLO
A4: Subpresupuesto | B4: 002 | C4: PLAN DE MANTENIMIENTO CORRECTIVO Y PREVENTIVO
A5: Cliente | C5: MUNICIPALIDAD DISTRITAL DE YARINACOCHA | E5: Costo al | F5: 46236
A6: Lugar | C6: UCAYALI - CORONEL PORTILLO - PANAILLO
A8: Item | B8: Descripción | C8: Und. | D8: Metrado | E8: Precio S/. | F8: Parcial S/.
A9: 01 | B9: MANTENIMIENTO DE CASTILLO DE CONCRETO | F9: =SUM(F10,F14) -> 12652.28
A10: 01.01 | B10: TRABAJOS PRELIMINARES | F10: =SUM(F11:F13) -> 4327.81
A11: 01.01.01 | B11: LIJADO DE COLUMNAS DE CONCRETO | C11: m2 | D11: 79.63 | E11: ='Análisis Precios Unitarios'!G7 -> 18.2409 | F11: =ROUND(D11*E11, 2) -> 1452.52
A12: 01.01.02 | B12: LIJADO DE VIGAS DE CONCRETO | C12: m2 | D12: 59.98 | E12: ='Análisis Precios Unitarios'!G21 -> 18.4209 | F12: =ROUND(D12*E12, 2) -> 1104.89
A13: 01.01.03 | B13: LIJADO DE PAREDES DE CONCRETO EN RESERVORIO | C13: m2 | D13: 165.12 | E13: ='Análisis Precios Unitarios'!G35 -> 10.7219 | F13: =ROUND(D13*E13, 2) -> 1770.4
A14: 01.02 | B14: PINTURA | F14: =SUM(F15:F17) -> 8324.47
A15: 01.02.01 | B15: PINTURA ESMALTE EN COLUMNAS DE CONCRETO (2 MANOS) | C15: m2 | D15: 79.63 | E15: ='Análisis Precios Unitarios'!G49 -> 29.081 | F15: =ROUND(D15*E15, 2) -> 2315.72
A16: 01.02.02 | B16: PINTURA ESMALTE EN VIGAS DE CONCRETO (2 MANOS) | C16: m2 | D16: 59.98 | E16: ='Análisis Precios Unitarios'!G66 -> 25.081 | F16: =ROUND(D16*E16, 2) -> 1504.36
A17: 01.02.03 | B17: PINTURA ESMALTE EN PAREDES DE CONCRETO (2 MANOS) | C17: m2 | D17: 165.12 | E17: ='Análisis Precios Unitarios'!G83 -> 27.2795 | F17: =ROUND(D17*E17, 2) -> 4504.39
A18: 03 | B18: MANTENIMIENTO DE CERCO METALICO | F18: =SUM(F19,F21) -> 4819.41
A19: 03.01 | B19: TRABAJOS PRELIMINARES | F19: =SUM(F20) -> 1622.32
A20: 03.01.01 | B20: LIJADO DE SUPERFICIE METALICA | C20: m2 | D20: 144.4 | E20: ='Análisis Precios Unitarios'!G100 -> 11.2349 | F20: =ROUND(D20*E20, 2) -> 1622.32
A21: 03.02 | B21: PINTURA | F21: =SUM(F22) -> 3197.09
A22: 03.02.01 | B22: PINTURA ANTICORROSIVA EN SUPERFICIE METALICA | C22: m2 | D22: 144.4 | E22: ='Análisis Precios Unitarios'!G115 -> 22.1405 | F22: =ROUND(D22*E22, 2) -> 3197.09
A23: 04 | B23: VARIOS | F23: =SUM(F24,F26,F28,F30) -> 3364.8
A24: 04.01 | B24: KIT DE HERRAMIENTAS | F24: =SUM(F25) -> 2415.8
A25: 04.01.01 | B25: SUMINISTRO Y ENTREGA DE KIT DE HERRAMIENTAS (FORMATO SEGÚN ACTA DEL MVCS) | C25: GLB | D25: 1 | E25: ='Análisis Precios Unitarios'!G132 -> 2415.8 | F25: =ROUND(D25*E25, 2) -> 2415.8
A26: 04.02 | B26: SEGURIDAD Y SALUD | F26: =SUM(F27) -> 249
A27: 04.02.01 | B27: EQUIPOS DE PROTECCION PERSONAL | C27: und | D27: 3 | E27: ='Análisis Precios Unitarios'!G173 -> 83 | F27: =ROUND(D27*E27, 2) -> 249
A28: 04.03 | B28: TRANSPORTE | F28: =SUM(F29) -> 500
A29: 04.03.01 | B29: MOVILIZACIÓN Y TRANSPORTE DE MATERIALES, EQUIPOS Y HERRAMIENTAS | C29: GLB | D29: 1 | E29: ='Análisis Precios Unitarios'!G184 -> 500 | F29: =ROUND(D29*E29, 2) -> 500
A30: 04.04 | B30: CAPACITACION | F30: =SUM(F31) -> 200
A31: 04.04.01 | B31: CAPACITACION DE OPERADORES Y JASS DE LA LOCALIDAD | C31: GLB | D31: 1 | E31: ='Análisis Precios Unitarios'!G192 -> 200 | F31: =ROUND(D31*E31, 2) -> 200
B33: COSTO DIRECTO | F33: =SUM(F9,F18,F23) -> 20836.49
B34: Gastos Generales 10% CD | F34: =ROUND(F33*0.1, 2) -> 2083.65
B35: Utilidad 10% CD | F35: =ROUND(F33*0.1, 2) -> 2083.65
B36: SUBTOTAL | F36: =F33+F34+F35 -> 25003.79
B37: IGV (18%) | F37: =ROUND(F36*0.18, 2) -> 4500.68
B39: TOTAL DEL PRESUPUESTO | F39: =F36+F37 -> 29504.47
B41: SON: VEINTINUEVE MIL QUINIENTOS CUATRO Y 47/100 SOLES

Sheet Análisis Precios Unitarios
A1: Análisis de precios unitarios
A3: Presupuesto | B3: 1101030 | C3: PLAN DE MANTENIMIENTO - PANAILLO
A4: Subpresupuesto | B4: 002 | C4: PLAN DE MANTENIMIENTO CORRECTIVO Y PREVENTIVO | F4: Fecha presupuesto | G4: 02/08/2026
A6: Partida | B6: 01.01.01 LIJADO DE COLUMNAS DE CONCRETO | F6: Und. | G6: m2
A7: Rendimiento | B7: m2/DIA 20.0000 | D7: EQ. | E7: 20 | F7: Costo unitario directo por : | G7: =SUM(G11,G14,G17) -> 18.2409
A8: Código | B8: Descripción Recurso | C8: Unidad | D8: Cuadrilla | E8: Cantidad | F8: Precio S/. | G8: Parcial S/.
B9: MANO DE OBRA
A10: 0147010004 | B10: PEON | C10: hh | D10: 2 | E10: =8*D10/$E$7 -> 0.8 | F10: 21.29 | G10: =ROUND(E10*F10, 2) -> 17.03
G11: =SUM(G10) -> 17.03
B12: MATERIALES
A13: 0239020037 | B13: LIJA #40 (PLIEGO) | C13: und | E13: 0.2 | F13: 3.5 | G13: =ROUND(E13*F13, 2) -> 0.7
G14: =SUM(G13) -> 0.7
B15: EQUIPOS
A16: 0337010001 | B16: HERRAMIENTAS MANUALES | C16: %MO | E16: 3 | F16: =G11 -> 17.03 | G16: =ROUND(E16*F16, 2)/100 -> 0.5109
G17: =SUM(G16) -> 0.5109
A20: Partida | B20: 01.01.02 LIJADO DE VIGAS DE CONCRETO | F20: Und. | G20: m2
A21: Rendimiento | B21: m2/DIA 20.0000 | D21: EQ. | E21: 20 | F21: Costo unitario directo por : | G21: =SUM(G25,G28,G31) -> 18.4209
A22: Código | B22: Descripción Recurso | C22: Unidad | D22: Cuadrilla | E22: Cantidad | F22: Precio S/. | G22: Parcial S/.
B23: MANO DE OBRA
A24: 0147010004 | B24: PEON | C24: hh | D24: 2 | E24: =8*D24/$E$21 -> 0.8 | F24: 21.29 | G24: =ROUND(E24*F24, 2) -> 17.03
G25: =SUM(G24) -> 17.03
B26: MATERIALES
A27: 0239020037 | B27: LIJA #40 (PLIEGO) | C27: und | E27: 0.25 | F27: 3.5 | G27: =ROUND(E27*F27, 2) -> 0.88
G28: =SUM(G27) -> 0.88
B29: EQUIPOS
A30: 0337010001 | B30: HERRAMIENTAS MANUALES | C30: %MO | E30: 3 | F30: =G25 -> 17.03 | G30: =ROUND(E30*F30, 2)/100 -> 0.5109
G31: =SUM(G30) -> 0.5109
A34: Partida | B34: 01.01.03 LIJADO DE PAREDES DE CONCRETO EN RESERVORIO | F34: Und. | G34: m2
A35: Rendimiento | B35: m2/DIA 35.0000 | D35: EQ. | E35: 35 | F35: Costo unitario directo por : | G35: =SUM(G39,G42,G45) -> 10.7219
A36: Código | B36: Descripción Recurso | C36: Unidad | D36: Cuadrilla | E36: Cantidad | F36: Precio S/. | G36: Parcial S/.
B37: MANO DE OBRA
A38: 0147010004 | B38: PEON | C38: hh | D38: 2 | E38: =8*D38/$E$35 -> 0.45714286 | F38: 21.29 | G38: =ROUND(E38*F38, 2) -> 9.73
G39: =SUM(G38) -> 9.73
B40: MATERIALES
A41: 0239020037 | B41: LIJA #40 (PLIEGO) | C41: und | E41: 0.2 | F41: 3.5 | G41: =ROUND(E41*F41, 2) -> 0.7
G42: =SUM(G41) -> 0.7
B43: EQUIPOS
A44: 0337010001 | B44: HERRAMIENTAS MANUALES | C44: %MO | E44: 3 | F44: =G39 -> 9.73 | G44: =ROUND(E44*F44, 2)/100 -> 0.2919
G45: =SUM(G44) -> 0.2919
A48: Partida | B48: 01.02.01 PINTURA ESMALTE EN COLUMNAS DE CONCRETO (2 MANOS) | F48: Und. | G48: m2
A49: Rendimiento | B49: m2/DIA 35.0000 | D49: EQ. | E49: 35 | F49: Costo unitario directo por : | G49: =SUM(G54,G58,G62) -> 29.081
A50: Código | B50: Descripción Recurso | C50: Unidad | D50: Cuadrilla | E50: Cantidad | F50: Precio S/. | G50: Parcial S/.
B51: MANO DE OBRA
A52: 0147010002 | B52: OPERARIO | C52: hh | D52: 1 | E52: =8*D52/$E$49 -> 0.22857143 | F52: 29.9 | G52: =ROUND(E52*F52, 2) -> 6.83
A53: 0147010004 | B53: PEON | C53: hh | D53: 1 | E53: =8*D53/$E$49 -> 0.22857143 | F53: 21.29 | G53: =ROUND(E53*F53, 2) -> 4.87
G54: =SUM(G52:G53) -> 11.7
B55: MATERIALES
A56: 0254020000 | B56: PINTURA ESMALTE | C56: gln | E56: 0.12 | F56: 57 | G56: =ROUND(E56*F56, 2) -> 6.84
A57: 0253030027 | B57: THINER | C57: gln | E57: 0.03 | F57: 35 | G57: =ROUND(E57*F57, 2) -> 1.05
G58: =SUM(G56:G57) -> 7.89
B59: EQUIPOS
A60: 0337010001 | B60: HERRAMIENTAS MANUALES | C60: %MO | E60: 3 | F60: =G54 -> 11.7 | G60: =ROUND(E60*F60, 2)/100 -> 0.351
A61: 0348800000 | B61: ANDAMIO | C61: HE | D61: 2 | E61: =8*D61/$E$49 -> 0.45714286 | F61: 20 | G61: =ROUND(E61*F61, 2) -> 9.14
G62: =SUM(G60:G61) -> 9.491
A65: Partida | B65: 01.02.02 PINTURA ESMALTE EN VIGAS DE CONCRETO (2 MANOS) | F65: Und. | G65: m2
A66: Rendimiento | B66: m2/DIA 35.0000 | D66: EQ. | E66: 35 | F66: Costo unitario directo por : | G66: =SUM(G71,G75,G79) -> 25.081
A67: Código | B67: Descripción Recurso | C67: Unidad | D67: Cuadrilla | E67: Cantidad | F67: Precio S/. | G67: Parcial S/.
B68: MANO DE OBRA
A69: 0147010002 | B69: OPERARIO | C69: hh | D69: 1 | E69: =8*D69/$E$66 -> 0.22857143 | F69: 29.9 | G69: =ROUND(E69*F69, 2) -> 6.83
A70: 0147010004 | B70: PEON | C70: hh | D70: 1 | E70: =8*D70/$E$66 -> 0.22857143 | F70: 21.29 | G70: =ROUND(E70*F70, 2) -> 4.87
G71: =SUM(G69:G70) -> 11.7
B72: MATERIALES
A73: 0253030027 | B73: THINER | C73: gln | E73: 0.03 | F73: 35 | G73: =ROUND(E73*F73, 2) -> 1.05
A74: 0254020000 | B74: PINTURA ESMALTE | C74: gln | E74: 0.13 | F74: 57 | G74: =ROUND(E74*F74, 2) -> 7.41
G75: =SUM(G73:G74) -> 8.46
B76: EQUIPOS
A77: 0337010001 | B77: HERRAMIENTAS MANUALES | C77: %MO | E77: 3 | F77: =G71 -> 11.7 | G77: =ROUND(E77*F77, 2)/100 -> 0.351
A78: 0348800000 | B78: ANDAMIO | C78: HE | D78: 1 | E78: =8*D78/$E$66 -> 0.22857143 | F78: 20 | G78: =ROUND(E78*F78, 2) -> 4.57
G79: =SUM(G77:G78) -> 4.921
A82: Partida | B82: 01.02.03 PINTURA ESMALTE EN PAREDES DE CONCRETO (2 MANOS) | F82: Und. | G82: m2
A83: Rendimiento | B83: m2/DIA 30.0000 | D83: EQ. | E83: 30.0000 | F83: Costo unitario directo por : | G83: =SUM(G88,G92,G96) -> 27.2795
A84: Código | B84: Descripción Recurso | C84: Unidad | D84: Cuadrilla | E84: Cantidad | F84: Precio S/. | G84: Parcial S/.
B85: MANO DE OBRA
A86: 0147010002 | B86: OPERARIO | C86: hh | D86: 1 | E86: =8*D86/$E$83 -> 0.26666667 | F86: 29.9 | G86: =ROUND(E86*F86, 2) -> 7.97
A87: 0147010004 | B87: PEON | C87: hh | D87: 1 | E87: =8*D87/$E$83 -> 0.26666667 | F87: 21.29 | G87: =ROUND(E87*F87, 2) -> 5.68
G88: =SUM(G86:G87) -> 13.65
B89: MATERIALES
A90: 0253030027 | B90: THINER | C90: gln | E90: 0.03 | F90: 35 | G90: =ROUND(E90*F90, 2) -> 1.05
A91: 0254110096 | B91: PINTURA ESMALTE | C91: gln | E91: 0.12 | F91: 57 | G91: =ROUND(E91*F91, 2) -> 6.84
G92: =SUM(G90:G91) -> 7.89
B93: EQUIPOS
A94: 0337010001 | B94: HERRAMIENTAS MANUALES | C94: %MO | E94: 3 | F94: =G88 -> 13.65 | G94: =ROUND(E94*F94, 2)/100 -> 0.4095
A95: 0348800000 | B95: ANDAMIO | C95: HE | D95: 1 | E95: =8*D95/$E$83 -> 0.26666667 | F95: 20 | G95: =ROUND(E95*F95, 2) -> 5.33
G96: =SUM(G94:G95) -> 5.7395
A99: Partida | B99: 03.01.01 LIJADO DE SUPERFICIE METALICA | F99: Und. | G99: m2
A100: Rendimiento | B100: m2/DIA 20.0000 | D100: EQ. | E100: 20 | F100: Costo unitario directo por : | G100: =SUM(G105,G108,G111) -> 11.2349
A101: Código | B101: Descripción Recurso | C101: Unidad | D101: Cuadrilla | E101: Cantidad | F101: Precio S/. | G101: Parcial S/.
B102: MANO DE OBRA
A103: 0147010002 | B103: OPERARIO | C103: hh | D103: 0.5 | E103: =8*D103/$E$100 -> 0.2 | F103: 29.9 | G103: =ROUND(E103*F103, 2) -> 5.98
A104: 0147010004 | B104: PEON | C104: hh | D104: 0.1 | E104: =8*D104/$E$100 -> 0.04 | F104: 21.29 | G104: =ROUND(E104*F104, 2) -> 0.85
G105: =SUM(G103:G104) -> 6.83
B106: MATERIALES
A107: 0239020027 | B107: LIJA DE FIERRO # 80 | C107: pza | E107: 1.5 | F107: 2.8 | G107: =ROUND(E107*F107, 2) -> 4.2
G108: =SUM(G107) -> 4.2
B109: EQUIPOS
A110: 0337010001 | B110: HERRAMIENTAS MANUALES | C110: %MO | E110: 3 | F110: =G105 -> 6.83 | G110: =ROUND(E110*F110, 2)/100 -> 0.2049
G111: =SUM(G110) -> 0.2049
A114: Partida | B114: 03.02.01 PINTURA ANTICORROSIVA EN SUPERFICIE METALICA | F114: Und. | G114: m2
A115: Rendimiento | B115: m2/DIA 15.0000 | D115: EQ. | E115: 15.0000 | F115: Costo unitario directo por : | G115: =SUM(G119,G125,G128) -> 22.1405
A116: Código | B116: Descripción Recurso | C116: Unidad | D116: Cuadrilla | E116: Cantidad | F116: Precio S/. | G116: Parcial S/.
...

Sheet Relación de Insumos
A1: Relación de Insumos
A3: Presupuesto | B3: 1101030 | C3: PLAN DE MANTENIMIENTO - PANAILLO
A4: Subpresupuesto | B4: 002 | C4: PLAN DE MANTENIMIENTO CORRECTIVO Y PREVENTIVO
A5: Cliente | C5: MUNICIPALIDAD DISTRITAL DE YARINACOCHA | E5: Costo al | F5: 28/02/2026
A6: Lugar | C6: UCAYALI - CORONEL PORTILLO - PANAILLO
A8: Código | B8: Descripción Insumo | C8: Unidad | D8: Cantidad | E8: Precio S/. | F8: Parcial S/.
B9: MANO DE OBRA
A10: 0147010002 | B10: OPERARIO | C10: hh | D10: ='Análisis Precios Unitarios'!E52*Presupuesto!D15+'Análisis Precios Unitarios'!E69*Presupuesto!D16+'Análisis Precios Unitarios'!E86*Presupuesto!D17+'Análisis Precios Unitarios'!E103*Presupuesto!D20 -> 104.82286 | E10: =F10/D10 -> 29.889041 | F10: ='Análisis Precios Unitarios'!G52*Presupuesto!D15+'Análisis Precios Unitarios'!G69*Presupuesto!D16+'Análisis Precios Unitarios'!G86*Presupuesto!D17+'Análisis Precios Unitarios'!G103*Presupuesto!D20 -> 3133.0547
A11: 0147010004 | B11: PEON | C11: hh | D11: ='Análisis Precios Unitarios'!E10*Presupuesto!D11+'Análisis Precios Unitarios'!E24*Presupuesto!D12+'Análisis Precios Unitarios'!E38*Presupuesto!D13+'Análisis Precios Unitarios'!E53*Presupuesto!D15+'Análisis Precios Unitarios'!E70*Presupuesto!D16+'Análisis Precios Unitarios'!E87*Presupuesto!D17+'Análisis Precios Unitarios'!E104*Presupuesto!D20+'Análisis Precios Unitarios'!E118*Presupuesto!D22 -> 345.90362 | E11: =F11/D11 -> 21.288121 | F11: ='Análisis Precios Unitarios'!G10*Presupuesto!D11+'Análisis Precios Unitarios'!G24*Presupuesto!D12+'Análisis Precios Unitarios'!G38*Presupuesto!D13+'Análisis Precios Unitarios'!G53*Presupuesto!D15+'Análisis Precios Unitarios'!G70*Presupuesto!D16+'Análisis Precios Unitarios'!G87*Presupuesto!D17+'Análisis Precios Unitarios'!G104*Presupuesto!D20+'Análisis Precios Unitarios'!G118*Presupuesto!D22 -> 7363.6382
F12: =SUM(F10:F11) -> 10496.693
B13: MATERIALES
A14: 0201020068 | B14: ACEITE DE MAQUINA 3 EN 1.60 ML | C14: und | D14: ='Análisis Precios Unitarios'!E142*Presupuesto!D25 -> 1 | E14: =F14/D14 -> 10 | F14: ='Análisis Precios Unitarios'!G142*Presupuesto!D25 -> 10
A15: 0205010034 | B15: CASCO DE SEGURIDAD | C15: und | D15: ='Análisis Precios Unitarios'!E143*Presupuesto!D25+'Análisis Precios Unitarios'!E176*Presupuesto!D27 -> 5 | E15: =F15/D15 -> 15 | F15: ='Análisis Precios Unitarios'!G143*Presupuesto!D25+'Análisis Precios Unitarios'!G176*Presupuesto!D27 -> 75
A16: 0207020017 | B16: ALICATE | C16: und | D16: ='Análisis Precios Unitarios'!E144*Presupuesto!D25 -> 1 | E16: =F16/D16 -> 12.5 | F16: ='Análisis Precios Unitarios'!G144*Presupuesto!D25 -> 12.5
A17: 0207020018 | B17: COMBA DE 6 LBS | C17: und | D17: ='Análisis Precios Unitarios'!E145*Presupuesto!D25 -> 1 | E17: =F17/D17 -> 45 | F17: ='Análisis Precios Unitarios'!G145*Presupuesto!D25 -> 45
A18: 0207020019 | B18: LLAVE STILSON DE 18" | C18: und | D18: ='Análisis Precios Unitarios'!E146*Presupuesto!D25 -> 1 | E18: =F18/D18 -> 184.9 | F18: ='Análisis Precios Unitarios'!G146*Presupuesto!D25 -> 184.9
A19: 0207020020 | B19: ESCOFINA TIPO LUNA DE 1/2" | C19: und | D19: ='Análisis Precios Unitarios'!E147*Presupuesto!D25 -> 1 | E19: =F19/D19 -> 20 | F19: ='Análisis Precios Unitarios'!G147*Presupuesto!D25 -> 20
A20: 0207020021 | B20: MASCARILLA PROTECTORA CON FILTRO ANTIGAS | C20: und | D20: ='Análisis Precios Unitarios'!E148*Presupuesto!D25 -> 2 | E20: =F20/D20 -> 83.7 | F20: ='Análisis Precios Unitarios'!G148*Presupuesto!D25 -> 167.4
A21: 0207020022 | B21: MARTILLO CARPINTERIA | C21: und | D21: ='Análisis Precios Unitarios'!E149*Presupuesto!D25 -> 1 | E21: =F21/D21 -> 31.5 | F21: ='Análisis Precios Unitarios'!G149*Presupuesto!D25 -> 31.5
A22: 0207020023 | B22: PALA RECTA | C22: und | D22: ='Análisis Precios Unitarios'!E150*Presupuesto!D25 -> 1 | E22: =F22/D22 -> 44.9 | F22: ='Análisis Precios Unitarios'!G150*Presupuesto!D25 -> 44.9
A23: 0207020024 | B23: MACHETE O CHAFLAN | C23: und | D23: ='Análisis Precios Unitarios'!E151*Presupuesto!D25 -> 1 | E23: =F23/D23 -> 19.9 | F23: ='Análisis Precios Unitarios'!G151*Presupuesto!D25 -> 19.9
A24: 0207020025 | B24: HOJAS DE SIERRA | C24: und | D24: ='Análisis Precios Unitarios'!E152*Presupuesto!D25 -> 3 | E24: =F24/D24 -> 8.9 | F24: ='Análisis Precios Unitarios'!G152*Presupuesto!D25 -> 26.7
A25: 0207020026 | B25: WINCHA DE 5M | C25: und | D25: ='Análisis Precios Unitarios'!E153*Presupuesto!D25 -> 1 | E25: =F25/D25 -> 29.4 | F25: ='Análisis Precios Unitarios'!G153*Presupuesto!D25 -> 29.4
A26: 0207020027 | B26: CINCEL DE PUNTA Y PLANA | C26: PAR | D26: ='Análisis Precios Unitarios'!E154*Presupuesto!D25 -> 1 | E26: =F26/D26 -> 12.9 | F26: ='Análisis Precios Unitarios'!G154*Presupuesto!D25 -> 12.9
A27: 0210130059 | B27: PICO CON MANGO | C27: und | D27: ='Análisis Precios Unitarios'!E155*Presupuesto!D25 -> 1 | E27: =F27/D27 -> 94.2 | F27: ='Análisis Precios Unitarios'!G155*Presupuesto!D25 -> 94.2
A28: 0210210043 | B28: BOTAS DE JEBE | C28: PAR | D28: ='Análisis Precios Unitarios'!E177*Presupuesto!D27 -> 3 | E28: =F28/D28 -> 35 | F28: ='Análisis Precios Unitarios'!G177*Presupuesto!D27 -> 105
A29: 0226310057 | B29: CHALECO REFLECTIVO | C29: und | D29: ='Análisis Precios Unitarios'!E178*Presupuesto!D27 -> 3 | E29: =F29/D29 -> 29 | F29: ='Análisis Precios Unitarios'!G178*Presupuesto!D27 -> 87
A30: 0226570002 | B30: LLAVE FRANCESA DE 15" | C30: und | D30: ='Análisis Precios Unitarios'!E156*Presupuesto!D25 -> 1 | E30: =F30/D30 -> 115 | F30: ='Análisis Precios Unitarios'!G156*Presupuesto!D25 -> 115
A31: 0229130010 | B31: CINTA TEFLON | C31: und | D31: ='Análisis Precios Unitarios'!E157*Presupuesto!D25 -> 3 | E31: =F31/D31 -> 3.5 | F31: ='Análisis Precios Unitarios'!G157*Presupuesto!D25 -> 10.5
A32: 0230010085 | B32: PEGAMENTO PVC 1/4 GALON | C32: und | D32: ='Análisis Precios Unitarios'!E158*Presupuesto!D25 -> 1 | E32: =F32/D32 -> 85 | F32: ='Análisis Precios Unitarios'!G158*Presupuesto!D25 -> 85
A33: 0230350007 | B33: MEDIDOR DE PLASTICO GRADUADO DE UN KILO PARA MEDIR CLORO | C33: und | D33: ='Análisis Precios Unitarios'!E159*Presupuesto!D25 -> 1 | E33: =F33/D33 -> 10 | F33: ='Análisis Precios Unitarios'!G159*Presupuesto!D25 -> 10
A34: 0230530013 | B34: ESCOBILLA DE PLASTICO CON ASA | C34: und | D34: ='Análisis Precios Unitarios'!E160*Presupuesto!D25 -> 2 | E34: =F34/D34 -> 10 | F34: ='Análisis Precios Unitarios'!G160*Presupuesto!D25 -> 20
A35: 0230530014 | B35: ESCOBA DE PLASTICO | C35: und | D35: ='Análisis Precios Unitarios'!E161*Presupuesto!D25 -> 1 | E35: =F35/D35 -> 21.5 | F35: ='Análisis Precios Unitarios'!G161*Presupuesto!D25 -> 21.5
A36: 0230700084 | B36: BALDE DE PLASTICO GRADUADO DE 20 LT. | C36: und | D36: ='Análisis Precios Unitarios'!E162*Presupuesto!D25 -> 1 | E36: =F36/D36 -> 25 | F36: ='Análisis Precios Unitarios'!G162*Presupuesto!D25 -> 25
A37: 0230750100 | B37: BLISTER DE PASTILLAS DPD | C37: und | D37: ='Análisis Precios Unitarios'!E163*Presupuesto!D25 -> 35 | E37: =F37/D37 -> 6 | F37: ='Análisis Precios Unitarios'!G163*Presupuesto!D25 -> 210
A38: 0230760075 | B38: COMPARADOR DE CLORO DIGITAL | C38: und | D38: ='Análisis Precios Unitarios'!E164*Presupuesto!D25 -> 1 | E38: =F38/D38 -> 450 | F38: ='Análisis Precios Unitarios'!G164*Presupuesto!D25 -> 450
A39: 0230920061 | B39: MANGUERA | C39: m | D39: ='Análisis Precios Unitarios'!E165*Presupuesto!D25 -> 30 | E39: =F39/D39 -> 4 | F39: ='Análisis Precios Unitarios'!G165*Presupuesto!D25 -> 120
A40: 0230990101 | B40: OVEROL | C40: und | D40: ='Análisis Precios Unitarios'!E166*Presupuesto!D25 -> 2 | E40: =F40/D40 -> 77 | F40: ='Análisis Precios Unitarios'!G166*Presupuesto!D25 -> 154
A41: 0232010095 | B41: TRANSPORTE DE EQUIPOS Y MATERIALES | C41: GLB | D41: ='Análisis Precios Unitarios'!E187*Presupuesto!D29 -> 1 | E41: =F41/D41 -> 500 | F41: ='Análisis Precios Unitarios'!G187*Presupuesto!D29 -> 500
A42: 0239020027 | B42: LIJA DE FIERRO # 80 | C42: pza | D42: ='Análisis Precios Unitarios'!E107*Presupuesto!D20 -> 216.6 | E42: =F42/D42 -> 2.8 | F42: ='Análisis Precios Unitarios'!G107*Presupuesto!D20 -> 606.48
A43: 0239020037 | B43: LIJA #40 (PLIEGO) | C43: und | D43: ='Análisis Precios Unitarios'!E13*Presupuesto!D11+'Análisis Precios Unitarios'!E27*Presupuesto!D12+'Análisis Precios Unitarios'!E41*Presupuesto!D13 -> 63.945 | E43: =F43/D43 -> 3.50469 | F43: ='Análisis Precios Unitarios'!G13*Presupuesto!D11+'Análisis Precios Unitarios'!G27*Presupuesto!D12+'Análisis Precios Unitarios'!G41*Presupuesto!D13 -> 224.1074
A44: 0239060024 | B44: WAYPE INDUSTRIAL | C44: kg | D44: ='Análisis Precios Unitarios'!E121*Presupuesto!D22 -> 7.22 | E44: =F44/D44 -> 8 | F44: ='Análisis Precios Unitarios'!G121*Presupuesto!D22 -> 57.76
A45: 0239070002 | B45: GUANTES DE HILO ROJO C/ PALMA DE LATEX | C45: PAR | D45: ='Análisis Precios Unitarios'!E167*Presupuesto!D25+'Análisis Precios Unitarios'!E179*Presupuesto!D27 -> 6 | E45: =F45/D45 -> 4 | F45: ='Análisis Precios Unitarios'!G167*Presupuesto!D25+'Análisis Precios Unitarios'!G179*Presupuesto!D27 -> 24
A46: 0239070003 | B46: GUANTES DE JEBE | C46: PAR | D46: ='Análisis Precios Unitarios'!E168*Presupuesto!D25 -> 2 | E46: =F46/D46 -> 6 | F46: ='Análisis Precios Unitarios'!G168*Presupuesto!D25 -> 12
A47: 0239070004 | B47: BOTAS DE JEBE | C47: PAR | D47: ='Análisis Precios Unitarios'!E135*Presupuesto!D25 -> 2 | E47: =F47/D47 -> 34.9 | F47: ='Análisis Precios Unitarios'!G135*Presupuesto!D25 -> 69.8
A48: 0239070005 | B48: DESTORNILLADOR PLANO | C48: und | D48: ='Análisis Precios Unitarios'!E136*Presupuesto!D25 -> 1 | E48: =F48/D48 -> 27.9 | F48: ='Análisis Precios Unitarios'!G136*Presupuesto!D25 -> 27.9
A49: 0239160010 | B49: BROCHA | C49: und | D49: ='Análisis Precios Unitarios'!E137*Presupuesto!D25 -> 1 | E49: =F49/D49 -> 20 | F49: ='Análisis Precios Unitarios'!G137*Presupuesto!D25 -> 20
A50: 0239990058 | B50: ARCO DE SIERRA | C50: und | D50: ='Análisis Precios Unitarios'!E138*Presupuesto!D25 -> 1 | E50: =F50/D50 -> 54 | F50: ='Análisis Precios Unitarios'!G138*Presupuesto!D25 -> 54
A51: 0239990059 | B51: CARRETILLA | C51: und | D51: ='Análisis Precios Unitarios'!E139*Presupuesto!D25 -> 1 | E51: =F51/D51 -> 210 | F51: ='Análisis Precios Unitarios'!G139*Presupuesto!D25 -> 210
A52: 0239990060 | B52: LENTES DE SEGURIDAD | C52: und | D52: ='Análisis Precios Unitarios'!E140*Presupuesto!D25 -> 2 | E52: =F52/D52 -> 4.9 | F52: ='Análisis Precios Unitarios'!G140*Presupuesto!D25 -> 9.8
A53: 0253030027 | B53: THINER | C53: gln | D53: ='Análisis Precios Unitarios'!E57*Presupuesto!D15+'Análisis Precios Unitarios'!E73*Presupuesto!D16+'Análisis Precios Unitarios'!E90*Presupuesto!D17 -> 9.1419 | E53: =F53/D53 -> 35 | F53: ='Análisis Precios Unitarios'!G57*Presupuesto!D15+'Análisis Precios Unitarios'!G73*Presupuesto!D16+'Análisis Precios Unitarios'!G90*Presupuesto!D17 -> 319.9665
A54: 0253030033 | B54: THINER ACRILICO | C54: gln | D54: ='Análisis Precios Unitarios'!E122*Presupuesto!D22 -> 3.61 | E54: =F54/D54 -> 18 | F54: ='Análisis Precios Unitarios'!G122*Presupuesto!D22 -> 64.98
A55: 0253030035 | B55: BROCHA 2 1/2" | C55: und | D55: ='Análisis Precios Unitarios'!E123*Presupuesto!D22 -> 14.44 | E55: =F55/D55 -> 12 | F55: ='Análisis Precios Unitarios'!G123*Presupuesto!D22 -> 173.28
A56: 0254020000 | B56: PINTURA ESMALTE | C56: gln | D56: ='Análisis Precios Unitarios'!E56*Presupuesto!D15+'Análisis Precios Unitarios'!E74*Presupuesto!D16 -> 17.353 | E56: =F56/D56 -> 57 | F56: ='Análisis Precios Unitarios'!G56*Presupuesto!D15+'Análisis Precios Unitarios'!G74*Presupuesto!D16 -> 989.121
A57: 0254060000 | B57: PINTURA ANTICORROSIVA | C57: gln | D57: ='Análisis Precios Unitarios'!E124*Presupuesto!D22 -> 17.328 | E57: =F57/D57 -> 70 | F57: ='Análisis Precios Unitarios'!G124*Presupuesto!D22 -> 1212.96
A58: 0254110096 | B58: PINTURA ESMALTE | C58: gln | D58: ='Análisis Precios Unitarios'!E91*Presupuesto!D17 -> 19.8144 | E58: =F58/D58 -> 57 | F58: ='Análisis Precios Unitarios'!G91*Presupuesto!D17 -> 1129.4208
A59: 0256990022 | B59: CAJA PLASTICA METALICA MADERA | C59: und | D59: ='Análisis Precios Unitarios'!E141*Presupuesto!D25 -> 1 | E59: =F59/D59 -> 50 | F59: ='Análisis Precios Unitarios'!G141*Presupuesto!D25 -> 50
F60: =SUM(F14:F59) -> 7942.8757
B61: EQUIPOS
A62: 0337010001 | B62: HERRAMIENTAS MANUALES | C62: %MO | D62: ='Análisis Precios Unitarios'!E16*Presupuesto!D11+'Análisis Precios Unitarios'!E30*Presupuesto!D12+'Análisis Precios Unitarios'!E44*Presupuesto!D13+'Análisis Precios Unitarios'!E60*Presupuesto!D15+'Análisis Precios Unitarios'!E77*Presupuesto!D16+'Análisis Precios Unitarios'!E94*Presupuesto!D17+'Análisis Precios Unitarios'!E110*Presupuesto!D20+'Análisis Precios Unitarios'!E127*Presupuesto!D22 -> 2694.78 | E62: =F62/D62 -> 0.11685584 | F62: ='Análisis Precios Unitarios'!G16*Presupuesto!D11+'Análisis Precios Unitarios'!G30*Presupuesto!D12+'Análisis Precios Unitarios'!G44*Presupuesto!D13+'Análisis Precios Unitarios'!G60*Presupuesto!D15+'Análisis Precios Unitarios'!G77*Presupuesto!D16+'Análisis Precios Unitarios'!G94*Presupuesto!D17+'Análisis Precios Unitarios'!G110*Presupuesto!D20+'Análisis Precios Unitarios'!G127*Presupuesto!D22 -> 314.90079
A63: 0337010005 | B63: SERVICIOS DE CAPACITACION Y ASISTENCIA TECNICA | C63: glb | D63: ='Análisis Precios Unitarios'!E195*Presupuesto!D31 -> 1 | E63: =F63/D63 -> 200 | F63: ='Análisis Precios Unitarios'!G195*Presupuesto!D31 -> 200
A64: 0348800000 | B64: ANDAMIO | C64: HE | D64: ='Análisis Precios Unitarios'!E61*Presupuesto!D15+'Análisis Precios Unitarios'!E78*Presupuesto!D16+'Análisis Precios Unitarios'!E95*Presupuesto!D17 -> 94.144 | E64: =F64/D64 -> 19.990827 | F64: ='Análisis Precios Unitarios'!G61*Presupuesto!D15+'Análisis Precios Unitarios'!G78*Presupuesto!D16+'Análisis Precios Unitarios'!G95*Presupuesto!D17 -> 1882.0164
F65: =SUM(F62:F64) -> 2396.9172
D67: Total | F67: =SUM(F12,F60,F65) -> 20836.486
